concerto/__init__.py
concerto/app.py
concerto/app_utils.py
concerto/constants.py
concerto/default_path.py
concerto/env.py
concerto/exceptions.py
concerto/introspection.py
concerto/io_utils.py
concerto/logger.py
concerto/python_env.py
concerto/registry.py
concerto/singleton.py
concerto/tensor.py
concerto/types.py
concerto/parser/__init__.py
concerto/plugins/__init__.py
concerto/plugins/plugin.py
concerto-0.5.1.dist-info/LICENSE
concerto-0.5.1.dist-info/METADATA
concerto-0.5.1.dist-info/WHEEL
concerto-0.5.1.dist-info/entry_points.txt
concerto-0.5.1.dist-info/top_level.txt
concerto-0.5.1.dist-info/RECORD
