Metadata-Version: 2.1
Name: concerto
Version: 0.5.1
Summary: a light framework for machine learning project
Home-page: https://github.com/samysung/concerto
Author: samy khelifi
Author-email: samy.khelifi@gmail.com
Project-URL: Bug Tracker, https://github.com/samysung/concerto/issues
Classifier: Programming Language :: Python :: 3
Classifier: Programming Language :: Python :: 3.10
Classifier: Programming Language :: Python :: 3.11
Classifier: Programming Language :: Python :: 3.12
Classifier: License :: OSI Approved :: Apache Software License
Classifier: Operating System :: OS Independent
Classifier: Topic :: Scientific/Engineering :: Artificial Intelligence
Classifier: Topic :: Scientific/Engineering :: Image Recognition
Requires-Python: >=3.10
License-File: LICENSE
Requires-Dist: omegaconf
Requires-Dist: jsonargparse
